secret_scanner/__init__.py
secret_scanner/cli.py
secret_scanner/core/__init__.py
secret_scanner/core/config.py
secret_scanner/core/detectors.py
secret_scanner/core/scanner.py
secret_scanner/utils/__init__.py
secret_scanner/utils/email_notifier.py
secret_scanner/utils/git_utils.py
secret_scanner/utils/mailersend_api.py
secret_scanner/utils/multi_project_scanner.py
secret_scanner/utils/platform_utils.py
secret_scanner/utils/pre_commit.py
secret_scanner/utils/report_generator.py
secret_scanner/utils/smtp_config.py
secrets_finder-1.0.0.dist-info/licenses/LICENSE
secrets_finder-1.0.0.dist-info/METADATA
secrets_finder-1.0.0.dist-info/WHEEL
secrets_finder-1.0.0.dist-info/entry_points.txt
secrets_finder-1.0.0.dist-info/top_level.txt
secrets_finder-1.0.0.dist-info/RECORD
