Metadata-Version: 2.4
Name: secrets-finder
Version: 1.0.0
Summary: A lightweight, extensible tool to automatically scan source code for hardcoded secrets and PII
Author-email: Saravanan Sathiyamoorthi <saravanansaro976@gmail.com>
Maintainer-email: Saravanan Sathiyamoorthi <saravanansaro976@gmail.com>
License: MIT
Project-URL: Homepage, https://gitlab.com/ox-saro/SecretDetection
Keywords: security,secrets,pii,detection,scanning,git,pre-commit,ci-cd,static-analysis,code-review
Classifier: Development Status :: 5 - Production/Stable
Classifier: Intended Audience :: Developers
Classifier: Intended Audience :: System Administrators
Classifier: Intended Audience :: Information Technology
Classifier: Operating System :: OS Independent
Classifier: Programming Language :: Python :: 3
Classifier: Programming Language :: Python :: 3.7
Classifier: Programming Language :: Python :: 3.8
Classifier: Programming Language :: Python :: 3.9
Classifier: Programming Language :: Python :: 3.10
Classifier: Programming Language :: Python :: 3.11
Classifier: Programming Language :: Python :: 3.12
Classifier: Topic :: Security
Classifier: Topic :: Software Development :: Quality Assurance
Classifier: Topic :: Software Development :: Testing
Classifier: Topic :: Software Development :: Libraries :: Python Modules
Classifier: Topic :: System :: Systems Administration
Classifier: Topic :: Utilities
Requires-Python: >=3.7
License-File: LICENSE
Requires-Dist: click>=8.0.0
Requires-Dist: colorama>=0.4.4
Requires-Dist: jinja2>=3.0.0
Requires-Dist: gitpython>=3.1.0
Requires-Dist: pyyaml>=6.0
Requires-Dist: rich>=12.0.0
Requires-Dist: typer>=0.7.0
Requires-Dist: pydantic>=1.10.0
Requires-Dist: python-multipart>=0.0.5
Requires-Dist: reportlab>=4.0.0
Requires-Dist: pathlib2>=2.3.0; python_version < "3.4"
Requires-Dist: typing-extensions>=4.0.0; python_version < "3.8"
Provides-Extra: pdf
Requires-Dist: weasyprint>=54.0; extra == "pdf"
Provides-Extra: reports
Requires-Dist: weasyprint>=54.0; extra == "reports"
Requires-Dist: reportlab>=4.0.0; extra == "reports"
Requires-Dist: lxml>=4.6.0; extra == "reports"
Requires-Dist: defusedxml>=0.7.0; extra == "reports"
Provides-Extra: dev
Requires-Dist: pytest>=6.0; extra == "dev"
Requires-Dist: pytest-cov>=2.0; extra == "dev"
Requires-Dist: pytest-mock>=3.0; extra == "dev"
Requires-Dist: black>=22.0; extra == "dev"
Requires-Dist: flake8>=4.0; extra == "dev"
Requires-Dist: mypy>=0.950; extra == "dev"
Requires-Dist: pre-commit>=2.0; extra == "dev"
Requires-Dist: tox>=3.24.0; extra == "dev"
Requires-Dist: bandit>=1.7.0; extra == "dev"
Provides-Extra: test
Requires-Dist: pytest>=6.0; extra == "test"
Requires-Dist: pytest-cov>=2.0; extra == "test"
Requires-Dist: pytest-mock>=3.0; extra == "test"
Requires-Dist: pytest-xdist>=2.4.0; extra == "test"
Requires-Dist: pytest-html>=3.1.0; extra == "test"
Provides-Extra: security
Requires-Dist: bandit>=1.7.0; extra == "security"
Requires-Dist: safety>=1.10.0; extra == "security"
Dynamic: license-file
